faudantic/__init__.py
faudantic/client.py
faudantic/helpers.py
faudantic/json.py
faudantic/orm.py
faudantic-0.1.7.dist-info/entry_points.txt
faudantic-0.1.7.dist-info/LICENSE
faudantic-0.1.7.dist-info/WHEEL
faudantic-0.1.7.dist-info/METADATA
faudantic-0.1.7.dist-info/RECORD
