Metadata-Version: 2.1
Name: faudantic
Version: 0.1.7
Summary: 
Author: Oscar Bahamonde
Author-email: oscar.bahamonde.dev@gmail.com
Requires-Python: >=3.8,<4.0
Classifier: Programming Language :: Python :: 3
Classifier: Programming Language :: Python :: 3.10
Classifier: Programming Language :: Python :: 3.8
Classifier: Programming Language :: Python :: 3.9
Requires-Dist: aiohttp (>=3.8.4,<4.0.0)
Requires-Dist: faunadb (>=4.5.0,<5.0.0)
Requires-Dist: pydantic[dotenv] (>=1.10.7,<2.0.0)
